{
  "offers": [
    {"reward":"coins","amount":750,"price":10,"currency":"gems","priority":1,"stock":10},
    {"reward":"coins","amount":1000,"price":12,"currency":"gems","priority":1,"stock":10},
    {"reward":"coins","amount":1250,"price":15,"currency":"gems","priority":2,"stock":5},
    {"reward":"coins","amount":1500,"price":17,"currency":"gems","priority":2,"stock":5},
    {"reward":"coins","amount":2500,"price":22,"currency":"gems","priority":3,"stock":2},
    {"reward":"gems","amount":3,"price":750,"currency":"coins","priority":2,"stock":5},
    {"reward":"gems","amount":5,"price":1000,"currency":"coins","priority":2,"stock":5},
    {"reward":"gems","amount":7,"price":1200,"currency":"coins","priority":3,"stock":2},
    {"reward":"gems","amount":10,"price":1500,"currency":"coins","priority":3,"stock":2},
    {"reward":"basic_crate","amount":1,"price":3,"currency":"gems","priority":1,"stock":5},
    {"reward":"basic_crate","amount":2,"price":5,"currency":"gems","priority":2,"stock":2},
    {"reward":"rare_crate","amount":1,"price":7,"currency":"gems","priority":1,"stock":5},
    {"reward":"rare_crate","amount":2,"price":12,"currency":"gems","priority":2,"stock":2},
    {"reward":"basic_crate","amount":1,"price":150,"currency":"coins","priority":3,"stock":1},
    {"reward":"rare_crate","amount":1,"price":500,"currency":"coins","priority":3,"stock":1}
  ],
  "sections": ["main","bundles","currencies","subscriptions"],
  "backdrop": "assets/shop/background.png"
}
